jepop/__init__.py
jepop/jepop.py
jepop/juniper_encap.py
jepop/juniper_ethernet.py
jepop-0.0.1.dist-info/LICENSE
jepop-0.0.1.dist-info/METADATA
jepop-0.0.1.dist-info/WHEEL
jepop-0.0.1.dist-info/entry_points.txt
jepop-0.0.1.dist-info/top_level.txt
jepop-0.0.1.dist-info/RECORD
