Metadata-Version: 2.1
Name: jepop
Version: 0.0.1
Summary: utility that pops Juniper Ethernet headers from a .pcap file
Home-page: https://github.com/Juniper/jepop
Author: Chris Jenn
Author-email: jnpr-community-netdev@juniper.net
License: GPL 2.0
Project-URL: Bug Tracker, https://github.com/Juniper/jepop/issues
Classifier: Development Status :: 5 - Production/Stable
Classifier: License :: OSI Approved :: Apache Software License
Classifier: Environment :: Console
Classifier: Operating System :: OS Independent
Classifier: Programming Language :: Python :: 3
Classifier: Topic :: System :: Networking
Requires-Python: >=3.6
License-File: LICENSE
Requires-Dist: scapy
